schedules/Errors.py
schedules/__init__.py
schedules/scheduler.py
schedules-1.3.dist-info/LICENSE
schedules-1.3.dist-info/METADATA
schedules-1.3.dist-info/WHEEL
schedules-1.3.dist-info/top_level.txt
schedules-1.3.dist-info/RECORD
