Metadata-Version: 2.1
Name: schedules
Version: 1.3
Summary: Create non-blocking scheduled tasks.
Home-page: https://github.com/YishaiYosifov/schedules
Author: YishaiYosifov
Author-email: yishai247@gmail.com
License: MIT
Keywords: schedule,task,nonblocking,scheduler,non-blocking,schedules
Platform: UNKNOWN
Classifier: Development Status :: 3 - Alpha
Classifier: Intended Audience :: Developers
Classifier: Topic :: Software Development :: Build Tools
Classifier: License :: OSI Approved :: MIT License
Classifier: Programming Language :: Python :: 3.4
Classifier: Programming Language :: Python :: 3.5
Classifier: Programming Language :: Python :: 3.6
Classifier: Programming Language :: Python :: 3.7
Classifier: Programming Language :: Python :: 3.8
Classifier: Programming Language :: Python :: 3.9
